CHANGES.rst
LICENSE.txt
MANIFEST.in
README.rst
setup.py
paxos/__init__.py
paxos/analyzer.py
paxos/messages.py
paxos/protocol.py
paxos/retries.py
paxos/sim.py
paxos/sim_dynamic.py
paxos/sim_failure.py
paxos/test.py
paxos/viz.py
paxos.egg-info/PKG-INFO
paxos.egg-info/SOURCES.txt
paxos.egg-info/dependency_links.txt
paxos.egg-info/top_level.txt