Metadata-Version: 1.1
Name: paxos
Version: 0.1
Summary: A demo implementation of the Paxos algorithm implemented in Python.
Home-page: https://github.com/gdub/python-paxos
Author: Gary Wilson Jr. and Michael Stathopoulos
Author-email: UNKNOWN
License: MIT
Platform: UNKNOWN
Classifier: Development Status :: 3 - Alpha
Classifier: Environment :: Console
Classifier: Intended Audience :: Developers
Classifier: Intended Audience :: Science/Research
Classifier: License :: OSI Approved :: MIT License
Classifier: Operating System :: OS Independent
Classifier: Programming Language :: Python
Classifier: Programming Language :: Python :: 3
Classifier: Programming Language :: Python :: 3.2
Classifier: Topic :: Communications
Classifier: Topic :: Scientific/Engineering
Classifier: Topic :: System :: Clustering
